[
  {
    "Riders All Time in All Classes": "AGOSTINI Giacomo",
    "Victories": 122,
    "2nd places": 35,
    "3rd places": 2,
    "Pole positions from '74 to 2022": 9,
    "Race fastest lap to 2022": 117,
    "World Championships": 15
  },
  {
    "Riders All Time in All Classes": "ROSSI Valentino",
    "Victories": 115,
    "2nd places": 67,
    "3rd places": 53,
    "Pole positions from '74 to 2022": 65,
    "Race fastest lap to 2022": 96,
    "World Championships": 9
  },
  {
    "Riders All Time in All Classes": "NIETO Angel",
    "Victories": 90,
    "2nd places": 35,
    "3rd places": 14,
    "Pole positions from '74 to 2022": 34,
    "Race fastest lap to 2022": 81,
    "World Championships": 13
  },
  {
    "Riders All Time in All Classes": "MARQUEZ Marc",
    "Victories": 85,
    "2nd places": 36,
    "3rd places": 17,
    "Pole positions from '74 to 2022": 90,
    "Race fastest lap to 2022": 75,
    "World Championships": 8
  },
  {
    "Riders All Time in All Classes": "HAILWOOD Mike",
    "Victories": 76,
    "2nd places": 25,
    "3rd places": 11,
    "Pole positions from '74 to 2022": "",
    "Race fastest lap to 2022": 79,
    "World Championships": 9
  },
  {
    "Riders All Time in All Classes": "LORENZO Jorge",
    "Victories": 68,
    "2nd places": 51,
    "3rd places": 33,
    "Pole positions from '74 to 2022": 69,
    "Race fastest lap to 2022": 37,
    "World Championships": 5
  },
  {
    "Riders All Time in All Classes": "PEDROSA Dani",
    "Victories": 54,
    "2nd places": 52,
    "3rd places": 47,
    "Pole positions from '74 to 2022": 49,
    "Race fastest lap to 2022": 64,
    "World Championships": 3
  },
  {
    "Riders All Time in All Classes": "DOOHAN Mick",
    "Victories": 54,
    "2nd places": 31,
    "3rd places": 10,
    "Pole positions from '74 to 2022": 58,
    "Race fastest lap to 2022": 46,
    "World Championships": 5
  },
  {
    "Riders All Time in All Classes": "READ Phil",
    "Victories": 52,
    "2nd places": 44,
    "3rd places": 25,
    "Pole positions from '74 to 2022": 5,
    "Race fastest lap to 2022": 36,
    "World Championships": 7
  },
  {
    "Riders All Time in All Classes": "REDMAN Jim",
    "Victories": 45,
    "2nd places": 33,
    "3rd places": 20,
    "Pole positions from '74 to 2022": "",
    "Race fastest lap to 2022": 35,
    "World Championships": 6
  },
  {
    "Riders All Time in All Classes": "STONER Casey",
    "Victories": 45,
    "2nd places": 17,
    "3rd places": 27,
    "Pole positions from '74 to 2022": 43,
    "Race fastest lap to 2022": 33,
    "World Championships": 2
  },
  {
    "Riders All Time in All Classes": "BIAGGI Max",
    "Victories": 42,
    "2nd places": 41,
    "3rd places": 28,
    "Pole positions from '74 to 2022": 56,
    "Race fastest lap to 2022": 42,
    "World Championships": 4
  },
  {
    "Riders All Time in All Classes": "MANG Anton",
    "Victories": 42,
    "2nd places": 25,
    "3rd places": 17,
    "Pole positions from '74 to 2022": 34,
    "Race fastest lap to 2022": 26,
    "World Championships": 5
  },
  {
    "Riders All Time in All Classes": "UBBIALI Carlo",
    "Victories": 39,
    "2nd places": 20,
    "3rd places": 9,
    "Pole positions from '74 to 2022": "",
    "Race fastest lap to 2022": 34,
    "World Championships": 9
  },
  {
    "Riders All Time in All Classes": "SURTEES John",
    "Victories": 38,
    "2nd places": 4,
    "3rd places": 3,
    "Pole positions from '74 to 2022": "",
    "Race fastest lap to 2022": 34,
    "World Championships": 7
  },
  {
    "Riders All Time in All Classes": "MARTINEZ Jorge",
    "Victories": 37,
    "2nd places": 14,
    "3rd places": 10,
    "Pole positions from '74 to 2022": 42,
    "Race fastest lap to 2022": 11,
    "World Championships": 4
  },
  {
    "Riders All Time in All Classes": "CADALORA Luca",
    "Victories": 34,
    "2nd places": 22,
    "3rd places": 16,
    "Pole positions from '74 to 2022": 29,
    "Race fastest lap to 2022": 30,
    "World Championships": 3
  },
  {
    "Riders All Time in All Classes": "DUKE Geoff",
    "Victories": 33,
    "2nd places": 7,
    "3rd places": 10,
    "Pole positions from '74 to 2022": "",
    "Race fastest lap to 2022": 29,
    "World Championships": 6
  },
  {
    "Riders All Time in All Classes": "LAWSON Eddie",
    "Victories": 31,
    "2nd places": 31,
    "3rd places": 16,
    "Pole positions from '74 to 2022": 18,
    "Race fastest lap to 2022": 21,
    "World Championships": 4
  },
  {
    "Riders All Time in All Classes": "BALLINGTON Kork",
    "Victories": 31,
    "2nd places": 9,
    "3rd places": 6,
    "Pole positions from '74 to 2022": 19,
    "Race fastest lap to 2022": 16,
    "World Championships": 4
  },
  {
    "Riders All Time in All Classes": "TAVERI Luigi",
    "Victories": 30,
    "2nd places": 33,
    "3rd places": 26,
    "Pole positions from '74 to 2022": "",
    "Race fastest lap to 2022": 28,
    "World Championships": 3
  },
  {
    "Riders All Time in All Classes": "CAPIROSSI Loris",
    "Victories": 29,
    "2nd places": 34,
    "3rd places": 36,
    "Pole positions from '74 to 2022": 41,
    "Race fastest lap to 2022": 32,
    "World Championships": 3
  },
  {
    "Riders All Time in All Classes": "LAZZARINI Eugenio",
    "Victories": 27,
    "2nd places": 35,
    "3rd places": 19,
    "Pole positions from '74 to 2022": 35,
    "Race fastest lap to 2022": 15,
    "World Championships": 3
  },
  {
    "Riders All Time in All Classes": "BIANCHI Pierpaolo",
    "Victories": 27,
    "2nd places": 17,
    "3rd places": 17,
    "Pole positions from '74 to 2022": 32,
    "Race fastest lap to 2022": 25,
    "World Championships": 3
  },
  {
    "Riders All Time in All Classes": "SPENCER Freddie",
    "Victories": 27,
    "2nd places": 10,
    "3rd places": 2,
    "Pole positions from '74 to 2022": 33,
    "Race fastest lap to 2022": 24,
    "World Championships": 3
  },
  {
    "Riders All Time in All Classes": "VIÑALES Maverick",
    "Victories": 25,
    "2nd places": 23,
    "3rd places": 20,
    "Pole positions from '74 to 2022": 24,
    "Race fastest lap to 2022": 22,
    "World Championships": 1
  },
  {
    "Riders All Time in All Classes": "SCHWANTZ Kevin",
    "Victories": 25,
    "2nd places": 13,
    "3rd places": 13,
    "Pole positions from '74 to 2022": 29,
    "Race fastest lap to 2022": 26,
    "World Championships": 1
  },
  {
    "Riders All Time in All Classes": "ANDERSON Hugh",
    "Victories": 25,
    "2nd places": 12,
    "3rd places": 11,
    "Pole positions from '74 to 2022": "",
    "Race fastest lap to 2022": 25,
    "World Championships": 4
  },
  {
    "Riders All Time in All Classes": "DOVIZIOSO Andrea",
    "Victories": 24,
    "2nd places": 39,
    "3rd places": 40,
    "Pole positions from '74 to 2022": 20,
    "Race fastest lap to 2022": 22,
    "World Championships": 1
  },
  {
    "Riders All Time in All Classes": "RAINEY Wayne",
    "Victories": 24,
    "2nd places": 22,
    "3rd places": 19,
    "Pole positions from '74 to 2022": 16,
    "Race fastest lap to 2022": 23,
    "World Championships": 3
  },
  {
    "Riders All Time in All Classes": "ROBERTS Kenny",
    "Victories": 24,
    "2nd places": 14,
    "3rd places": 6,
    "Pole positions from '74 to 2022": 22,
    "Race fastest lap to 2022": 27,
    "World Championships": 3
  },
  {
    "Riders All Time in All Classes": "VILLA Walter",
    "Victories": 24,
    "2nd places": 6,
    "3rd places": 6,
    "Pole positions from '74 to 2022": 21,
    "Race fastest lap to 2022": 20,
    "World Championships": 4
  },
  {
    "Riders All Time in All Classes": "SHEENE Barry",
    "Victories": 23,
    "2nd places": 13,
    "3rd places": 16,
    "Pole positions from '74 to 2022": 19,
    "Race fastest lap to 2022": 20,
    "World Championships": 2
  },
  {
    "Riders All Time in All Classes": "MELANDRI Marco",
    "Victories": 22,
    "2nd places": 20,
    "3rd places": 20,
    "Pole positions from '74 to 2022": 9,
    "Race fastest lap to 2022": 16,
    "World Championships": 1
  },
  {
    "Riders All Time in All Classes": "GRESINI Fausto",
    "Victories": 21,
    "2nd places": 15,
    "3rd places": 11,
    "Pole positions from '74 to 2022": 17,
    "Race fastest lap to 2022": 13,
    "World Championships": 2
  },
  {
    "Riders All Time in All Classes": "IVY Bill",
    "Victories": 21,
    "2nd places": 15,
    "3rd places": 6,
    "Pole positions from '74 to 2022": "",
    "Race fastest lap to 2022": 29,
    "World Championships": 1
  },
  {
    "Riders All Time in All Classes": "CRIVILLE Alex",
    "Victories": 20,
    "2nd places": 21,
    "3rd places": 25,
    "Pole positions from '74 to 2022": 12,
    "Race fastest lap to 2022": 20,
    "World Championships": 2
  },
  {
    "Riders All Time in All Classes": "WALDMANN Ralf",
    "Victories": 20,
    "2nd places": 15,
    "3rd places": 15,
    "Pole positions from '74 to 2022": 10,
    "Race fastest lap to 2022": 16,
    "World Championships": ""
  },
  {
    "Riders All Time in All Classes": "PROVINI Tarquinio",
    "Victories": 20,
    "2nd places": 10,
    "3rd places": 9,
    "Pole positions from '74 to 2022": "",
    "Race fastest lap to 2022": 26,
    "World Championships": 2
  },
  {
    "Riders All Time in All Classes": "LAVADO Carlos",
    "Victories": 19,
    "2nd places": 15,
    "3rd places": 8,
    "Pole positions from '74 to 2022": 22,
    "Race fastest lap to 2022": 13,
    "World Championships": 2
  },
  {
    "Riders All Time in All Classes": "HOCKING Gary",
    "Victories": 19,
    "2nd places": 12,
    "3rd places": 2,
    "Pole positions from '74 to 2022": "",
    "Race fastest lap to 2022": 21,
    "World Championships": 2
  },
  {
    "Riders All Time in All Classes": "TORMO Ricardo",
    "Victories": 19,
    "2nd places": 11,
    "3rd places": 6,
    "Pole positions from '74 to 2022": 23,
    "Race fastest lap to 2022": 4,
    "World Championships": 2
  },
  {
    "Riders All Time in All Classes": "DÖRFLINGER Stefan",
    "Victories": 18,
    "2nd places": 27,
    "3rd places": 13,
    "Pole positions from '74 to 2022": 34,
    "Race fastest lap to 2022": "",
    "World Championships": 4
  },
  {
    "Riders All Time in All Classes": "GARDNER Wayne",
    "Victories": 18,
    "2nd places": 20,
    "3rd places": 14,
    "Pole positions from '74 to 2022": 19,
    "Race fastest lap to 2022": 19,
    "World Championships": 1
  },
  {
    "Riders All Time in All Classes": "ANDERSSON Kent",
    "Victories": 18,
    "2nd places": 15,
    "3rd places": 20,
    "Pole positions from '74 to 2022": 4,
    "Race fastest lap to 2022": 9,
    "World Championships": 2
  },
  {
    "Riders All Time in All Classes": "HARADA Tetsuya",
    "Victories": 17,
    "2nd places": 26,
    "3rd places": 12,
    "Pole positions from '74 to 2022": 21,
    "Race fastest lap to 2022": 21,
    "World Championships": 1
  },
  {
    "Riders All Time in All Classes": "LUTHI Thomas",
    "Victories": 17,
    "2nd places": 23,
    "3rd places": 25,
    "Pole positions from '74 to 2022": 12,
    "Race fastest lap to 2022": 19,
    "World Championships": 1
  },
  {
    "Riders All Time in All Classes": "ELIAS Toni",
    "Victories": 17,
    "2nd places": 13,
    "3rd places": 13,
    "Pole positions from '74 to 2022": 12,
    "Race fastest lap to 2022": 12,
    "World Championships": 1
  },
  {
    "Riders All Time in All Classes": "BINDER Brad",
    "Victories": 17,
    "2nd places": 13,
    "3rd places": 8,
    "Pole positions from '74 to 2022": 7,
    "Race fastest lap to 2022": 12,
    "World Championships": 1
  },
  {
    "Riders All Time in All Classes": "KATO Daijiro",
    "Victories": 17,
    "2nd places": 5,
    "3rd places": 5,
    "Pole positions from '74 to 2022": 11,
    "Race fastest lap to 2022": 11,
    "World Championships": 1
  },
  {
    "Riders All Time in All Classes": "KALLIO Mika",
    "Victories": 16,
    "2nd places": 24,
    "3rd places": 9,
    "Pole positions from '74 to 2022": 18,
    "Race fastest lap to 2022": 12,
    "World Championships": ""
  },
  {
    "Riders All Time in All Classes": "ZARCO Johann",
    "Victories": 16,
    "2nd places": 22,
    "3rd places": 16,
    "Pole positions from '74 to 2022": 26,
    "Race fastest lap to 2022": 19,
    "World Championships": 2
  },
  {
    "Riders All Time in All Classes": "TEROL Nicolas",
    "Victories": 16,
    "2nd places": 17,
    "3rd places": 6,
    "Pole positions from '74 to 2022": 9,
    "Race fastest lap to 2022": 8,
    "World Championships": 1
  },
  {
    "Riders All Time in All Classes": "BAUTISTA Alvaro",
    "Victories": 16,
    "2nd places": 15,
    "3rd places": 18,
    "Pole positions from '74 to 2022": 18,
    "Race fastest lap to 2022": 22,
    "World Championships": 1
  },
  {
    "Riders All Time in All Classes": "OLIVEIRA Miguel",
    "Victories": 16,
    "2nd places": 13,
    "3rd places": 11,
    "Pole positions from '74 to 2022": 5,
    "Race fastest lap to 2022": 12,
    "World Championships": ""
  },
  {
    "Riders All Time in All Classes": "RINS Alex",
    "Victories": 15,
    "2nd places": 23,
    "3rd places": 17,
    "Pole positions from '74 to 2022": 17,
    "Race fastest lap to 2022": 17,
    "World Championships": ""
  },
  {
    "Riders All Time in All Classes": "PONS Sito",
    "Victories": 15,
    "2nd places": 16,
    "3rd places": 10,
    "Pole positions from '74 to 2022": 4,
    "Race fastest lap to 2022": 12,
    "World Championships": 2
  },
  {
    "Riders All Time in All Classes": "ESPARGARO Pol",
    "Victories": 15,
    "2nd places": 15,
    "3rd places": 22,
    "Pole positions from '74 to 2022": 20,
    "Race fastest lap to 2022": 16,
    "World Championships": 1
  },
  {
    "Riders All Time in All Classes": "DEGNER Ernst",
    "Victories": 15,
    "2nd places": 11,
    "3rd places": 12,
    "Pole positions from '74 to 2022": "",
    "Race fastest lap to 2022": 13,
    "World Championships": 1
  },
  {
    "Riders All Time in All Classes": "SAARINEN Jarno",
    "Victories": 15,
    "2nd places": 7,
    "3rd places": 10,
    "Pole positions from '74 to 2022": "",
    "Race fastest lap to 2022": 18,
    "World Championships": 1
  },
  {
    "Riders All Time in All Classes": "BRAUN Dieter",
    "Victories": 14,
    "2nd places": 17,
    "3rd places": 18,
    "Pole positions from '74 to 2022": "",
    "Race fastest lap to 2022": 10,
    "World Championships": 2
  },
  {
    "Riders All Time in All Classes": "ANSCHEIDT Hans-Georg",
    "Victories": 14,
    "2nd places": 13,
    "3rd places": 7,
    "Pole positions from '74 to 2022": "",
    "Race fastest lap to 2022": 12,
    "World Championships": 3
  },
  {
    "Riders All Time in All Classes": "CECOTTO Johnny",
    "Victories": 14,
    "2nd places": 10,
    "3rd places": 2,
    "Pole positions from '74 to 2022": 22,
    "Race fastest lap to 2022": 7,
    "World Championships": 1
  },
  {
    "Riders All Time in All Classes": "DE VRIES Jan",
    "Victories": 14,
    "2nd places": 9,
    "3rd places": 4,
    "Pole positions from '74 to 2022": "",
    "Race fastest lap to 2022": 13,
    "World Championships": 2
  },
  {
    "Riders All Time in All Classes": "BAGNAIA Francesco",
    "Victories": 14,
    "2nd places": 8,
    "3rd places": 11,
    "Pole positions from '74 to 2022": 13,
    "Race fastest lap to 2022": 11,
    "World Championships": 1
  },
  {
    "Riders All Time in All Classes": "SIMONCELLI Marco",
    "Victories": 14,
    "2nd places": 6,
    "3rd places": 11,
    "Pole positions from '74 to 2022": 15,
    "Race fastest lap to 2022": 9,
    "World Championships": 1
  },
  {
    "Riders All Time in All Classes": "RAUDIES Dirk",
    "Victories": 14,
    "2nd places": 6,
    "3rd places": 3,
    "Pole positions from '74 to 2022": 8,
    "Race fastest lap to 2022": 9,
    "World Championships": 1
  },
  {
    "Riders All Time in All Classes": "MAMOLA Randy",
    "Victories": 13,
    "2nd places": 25,
    "3rd places": 19,
    "Pole positions from '74 to 2022": 5,
    "Race fastest lap to 2022": 12,
    "World Championships": ""
  },
  {
    "Riders All Time in All Classes": "UEDA Noboru",
    "Victories": 13,
    "2nd places": 12,
    "3rd places": 14,
    "Pole positions from '74 to 2022": 19,
    "Race fastest lap to 2022": 11,
    "World Championships": ""
  },
  {
    "Riders All Time in All Classes": "KOCINSKI John",
    "Victories": 13,
    "2nd places": 12,
    "3rd places": 10,
    "Pole positions from '74 to 2022": 20,
    "Race fastest lap to 2022": 15,
    "World Championships": 1
  },
  {
    "Riders All Time in All Classes": "FENATI Romano",
    "Victories": 13,
    "2nd places": 11,
    "3rd places": 5,
    "Pole positions from '74 to 2022": 7,
    "Race fastest lap to 2022": 15,
    "World Championships": ""
  },
  {
    "Riders All Time in All Classes": "RABAT Tito",
    "Victories": 13,
    "2nd places": 10,
    "3rd places": 13,
    "Pole positions from '74 to 2022": 16,
    "Race fastest lap to 2022": 11,
    "World Championships": 1
  },
  {
    "Riders All Time in All Classes": "IANNONE Andrea",
    "Victories": 13,
    "2nd places": 8,
    "3rd places": 14,
    "Pole positions from '74 to 2022": 10,
    "Race fastest lap to 2022": 17,
    "World Championships": ""
  },
  {
    "Riders All Time in All Classes": "MARQUEZ Alex",
    "Victories": 12,
    "2nd places": 16,
    "3rd places": 12,
    "Pole positions from '74 to 2022": 15,
    "Race fastest lap to 2022": 17,
    "World Championships": 2
  },
  {
    "Riders All Time in All Classes": "POGGIALI Manuel",
    "Victories": 12,
    "2nd places": 10,
    "3rd places": 13,
    "Pole positions from '74 to 2022": 11,
    "Race fastest lap to 2022": 7,
    "World Championships": 2
  },
  {
    "Riders All Time in All Classes": "MIR Joan",
    "Victories": 12,
    "2nd places": 10,
    "3rd places": 11,
    "Pole positions from '74 to 2022": 2,
    "Race fastest lap to 2022": 7,
    "World Championships": 2
  },
  {
    "Riders All Time in All Classes": "PASINI Mattia",
    "Victories": 12,
    "2nd places": 8,
    "3rd places": 10,
    "Pole positions from '74 to 2022": 19,
    "Race fastest lap to 2022": 6,
    "World Championships": ""
  },
  {
    "Riders All Time in All Classes": "ANDERSON Fergus",
    "Victories": 12,
    "2nd places": 5,
    "3rd places": 7,
    "Pole positions from '74 to 2022": "",
    "Race fastest lap to 2022": 12,
    "World Championships": 2
  },
  {
    "Riders All Time in All Classes": "SAKATA Kazuto",
    "Victories": 11,
    "2nd places": 23,
    "3rd places": 7,
    "Pole positions from '74 to 2022": 29,
    "Race fastest lap to 2022": 19,
    "World Championships": 2
  },
  {
    "Riders All Time in All Classes": "KATAYAMA Takazumi",
    "Victories": 11,
    "2nd places": 11,
    "3rd places": 13,
    "Pole positions from '74 to 2022": 5,
    "Race fastest lap to 2022": 6,
    "World Championships": 1
  },
  {
    "Riders All Time in All Classes": "MARTIN Jorge",
    "Victories": 11,
    "2nd places": 10,
    "3rd places": 12,
    "Pole positions from '74 to 2022": 27,
    "Race fastest lap to 2022": 8,
    "World Championships": 1
  },
  {
    "Riders All Time in All Classes": "HAAS Werner",
    "Victories": 11,
    "2nd places": 7,
    "3rd places": "",
    "Pole positions from '74 to 2022": 1,
    "Race fastest lap to 2022": 11,
    "World Championships": 3
  },
  {
    "Riders All Time in All Classes": "MORBIDELLI Franco",
    "Victories": 11,
    "2nd places": 6,
    "3rd places": 10,
    "Pole positions from '74 to 2022": 8,
    "Race fastest lap to 2022": 14,
    "World Championships": 1
  },
  {
    "Riders All Time in All Classes": "SIMMONDS Dave",
    "Victories": 11,
    "2nd places": 6,
    "3rd places": 5,
    "Pole positions from '74 to 2022": "",
    "Race fastest lap to 2022": 7,
    "World Championships": 1
  },
  {
    "Riders All Time in All Classes": "UI Youichi",
    "Victories": 11,
    "2nd places": 6,
    "3rd places": 5,
    "Pole positions from '74 to 2022": 17,
    "Race fastest lap to 2022": 9,
    "World Championships": ""
  },
  {
    "Riders All Time in All Classes": "GOULD Rodney",
    "Victories": 10,
    "2nd places": 16,
    "3rd places": 8,
    "Pole positions from '74 to 2022": "",
    "Race fastest lap to 2022": 8,
    "World Championships": 1
  },
  {
    "Riders All Time in All Classes": "BRYANS Ralph",
    "Victories": 10,
    "2nd places": 15,
    "3rd places": 15,
    "Pole positions from '74 to 2022": "",
    "Race fastest lap to 2022": 7,
    "World Championships": 1
  },
  {
    "Riders All Time in All Classes": "HANSFORD Greg",
    "Victories": 10,
    "2nd places": 14,
    "3rd places": 1,
    "Pole positions from '74 to 2022": 11,
    "Race fastest lap to 2022": 5,
    "World Championships": ""
  },
  {
    "Riders All Time in All Classes": "QUARTARARO Fabio",
    "Victories": 10,
    "2nd places": 11,
    "3rd places": 5,
    "Pole positions from '74 to 2022": 19,
    "Race fastest lap to 2022": 12,
    "World Championships": 1
  },
  {
    "Riders All Time in All Classes": "BARBERA Hector",
    "Victories": 10,
    "2nd places": 9,
    "3rd places": 13,
    "Pole positions from '74 to 2022": 9,
    "Race fastest lap to 2022": 10,
    "World Championships": ""
  },
  {
    "Riders All Time in All Classes": "AZUMA Masao",
    "Victories": 10,
    "2nd places": 4,
    "3rd places": 6,
    "Pole positions from '74 to 2022": 2,
    "Race fastest lap to 2022": 12,
    "World Championships": ""
  },
  {
    "Riders All Time in All Classes": "FERNANDEZ Raul",
    "Victories": 10,
    "2nd places": 3,
    "3rd places": 3,
    "Pole positions from '74 to 2022": 13,
    "Race fastest lap to 2022": 8,
    "World Championships": ""
  },
  {
    "Riders All Time in All Classes": "GIBERNAU Sete",
    "Victories": 9,
    "2nd places": 14,
    "3rd places": 7,
    "Pole positions from '74 to 2022": 13,
    "Race fastest lap to 2022": 8,
    "World Championships": ""
  },
  {
    "Riders All Time in All Classes": "GIANOLA Ezio",
    "Victories": 9,
    "2nd places": 13,
    "3rd places": 8,
    "Pole positions from '74 to 2022": 12,
    "Race fastest lap to 2022": 10,
    "World Championships": ""
  },
  {
    "Riders All Time in All Classes": "SALOM Luis",
    "Victories": 9,
    "2nd places": 10,
    "3rd places": 6,
    "Pole positions from '74 to 2022": 4,
    "Race fastest lap to 2022": 7,
    "World Championships": ""
  },
  {
    "Riders All Time in All Classes": "AOYAMA Hiroshi",
    "Victories": 9,
    "2nd places": 8,
    "3rd places": 10,
    "Pole positions from '74 to 2022": 8,
    "Race fastest lap to 2022": 11,
    "World Championships": 1
  },
  {
    "Riders All Time in All Classes": "TALMACSI Gabor",
    "Victories": 9,
    "2nd places": 8,
    "3rd places": 9,
    "Pole positions from '74 to 2022": 11,
    "Race fastest lap to 2022": 9,
    "World Championships": 1
  },
  {
    "Riders All Time in All Classes": "LOCATELLI Roberto",
    "Victories": 9,
    "2nd places": 7,
    "3rd places": 9,
    "Pole positions from '74 to 2022": 18,
    "Race fastest lap to 2022": 10,
    "World Championships": 1
  },
  {
    "Riders All Time in All Classes": "AOKI Haruchika",
    "Victories": 9,
    "2nd places": 6,
    "3rd places": 5,
    "Pole positions from '74 to 2022": 6,
    "Race fastest lap to 2022": 5,
    "World Championships": 2
  },
  {
    "Riders All Time in All Classes": "LOWES Sam",
    "Victories": 9,
    "2nd places": 5,
    "3rd places": 10,
    "Pole positions from '74 to 2022": 17,
    "Race fastest lap to 2022": 9,
    "World Championships": ""
  },
  {
    "Riders All Time in All Classes": "SPAAN Hans",
    "Victories": 9,
    "2nd places": 5,
    "3rd places": 7,
    "Pole positions from '74 to 2022": 9,
    "Race fastest lap to 2022": 5,
    "World Championships": ""
  },
  {
    "Riders All Time in All Classes": "MILLER Jack",
    "Victories": 9,
    "2nd places": 4,
    "3rd places": 13,
    "Pole positions from '74 to 2022": 9,
    "Race fastest lap to 2022": 3,
    "World Championships": ""
  },
  {
    "Riders All Time in All Classes": "LOMAS Bill",
    "Victories": 9,
    "2nd places": 3,
    "3rd places": 4,
    "Pole positions from '74 to 2022": "",
    "Race fastest lap to 2022": 14,
    "World Championships": 2
  },
  {
    "Riders All Time in All Classes": "REGGIANI Loris",
    "Victories": 8,
    "2nd places": 14,
    "3rd places": 19,
    "Pole positions from '74 to 2022": 5,
    "Race fastest lap to 2022": 8,
    "World Championships": ""
  },
  {
    "Riders All Time in All Classes": "BASTIANINI Enea",
    "Victories": 8,
    "2nd places": 11,
    "3rd places": 17,
    "Pole positions from '74 to 2022": 9,
    "Race fastest lap to 2022": 8,
    "World Championships": 1
  },
  {
    "Riders All Time in All Classes": "SIMON Julian",
    "Victories": 8,
    "2nd places": 11,
    "3rd places": 7,
    "Pole positions from '74 to 2022": 10,
    "Race fastest lap to 2022": 12,
    "World Championships": 1
  },
  {
    "Riders All Time in All Classes": "LANSIVUORI Teuvo",
    "Victories": 8,
    "2nd places": 10,
    "3rd places": 9,
    "Pole positions from '74 to 2022": 12,
    "Race fastest lap to 2022": 12,
    "World Championships": ""
  },
  {
    "Riders All Time in All Classes": "FAUBEL Hector",
    "Victories": 8,
    "2nd places": 7,
    "3rd places": 11,
    "Pole positions from '74 to 2022": 3,
    "Race fastest lap to 2022": 9,
    "World Championships": ""
  },
  {
    "Riders All Time in All Classes": "MORTIMER Chas",
    "Victories": 7,
    "2nd places": 17,
    "3rd places": 15,
    "Pole positions from '74 to 2022": 3,
    "Race fastest lap to 2022": 5,
    "World Championships": ""
  },
  {
    "Riders All Time in All Classes": "JACQUE Olivier",
    "Victories": 7,
    "2nd places": 15,
    "3rd places": 13,
    "Pole positions from '74 to 2022": 17,
    "Race fastest lap to 2022": 9,
    "World Championships": 1
  },
  {
    "Riders All Time in All Classes": "SARRON Christian",
    "Victories": 7,
    "2nd places": 13,
    "3rd places": 17,
    "Pole positions from '74 to 2022": 11,
    "Race fastest lap to 2022": 10,
    "World Championships": 1
  },
  {
    "Riders All Time in All Classes": "BARROS Alex",
    "Victories": 7,
    "2nd places": 11,
    "3rd places": 14,
    "Pole positions from '74 to 2022": 5,
    "Race fastest lap to 2022": 14,
    "World Championships": ""
  },
  {
    "Riders All Time in All Classes": "CORTESE Sandro",
    "Victories": 7,
    "2nd places": 10,
    "3rd places": 12,
    "Pole positions from '74 to 2022": 10,
    "Race fastest lap to 2022": 11,
    "World Championships": 1
  },
  {
    "Riders All Time in All Classes": "ARMSTRONG Reg",
    "Victories": 7,
    "2nd places": 9,
    "3rd places": 13,
    "Pole positions from '74 to 2022": "",
    "Race fastest lap to 2022": 2,
    "World Championships": ""
  },
  {
    "Riders All Time in All Classes": "VAN KESSEL Henk",
    "Victories": 7,
    "2nd places": 9,
    "3rd places": 9,
    "Pole positions from '74 to 2022": 4,
    "Race fastest lap to 2022": "",
    "World Championships": 1
  },
  {
    "Riders All Time in All Classes": "CARRUTHERS Kel",
    "Victories": 7,
    "2nd places": 9,
    "3rd places": 6,
    "Pole positions from '74 to 2022": "",
    "Race fastest lap to 2022": 8,
    "World Championships": 1
  },
  {
    "Riders All Time in All Classes": "BRADL Stefan",
    "Victories": 7,
    "2nd places": 8,
    "3rd places": 4,
    "Pole positions from '74 to 2022": 8,
    "Race fastest lap to 2022": 5,
    "World Championships": 1
  },
  {
    "Riders All Time in All Classes": "VINCENT Arnaud",
    "Victories": 7,
    "2nd places": 8,
    "3rd places": 4,
    "Pole positions from '74 to 2022": 4,
    "Race fastest lap to 2022": 1,
    "World Championships": 1
  },
  {
    "Riders All Time in All Classes": "LORENZETTI Enrico",
    "Victories": 7,
    "2nd places": 7,
    "3rd places": 7,
    "Pole positions from '74 to 2022": "",
    "Race fastest lap to 2022": 6,
    "World Championships": 1
  },
  {
    "Riders All Time in All Classes": "PORTO Sebastian",
    "Victories": 7,
    "2nd places": 7,
    "3rd places": 5,
    "Pole positions from '74 to 2022": 11,
    "Race fastest lap to 2022": 8,
    "World Championships": ""
  },
  {
    "Riders All Time in All Classes": "CECCHINELLO Lucio",
    "Victories": 7,
    "2nd places": 7,
    "3rd places": 5,
    "Pole positions from '74 to 2022": 4,
    "Race fastest lap to 2022": 10,
    "World Championships": ""
  },
  {
    "Riders All Time in All Classes": "EKEROLD Jonnie",
    "Victories": 7,
    "2nd places": 6,
    "3rd places": 6,
    "Pole positions from '74 to 2022": 2,
    "Race fastest lap to 2022": "",
    "World Championships": 1
  },
  {
    "Riders All Time in All Classes": "UNCINI Franco",
    "Victories": 7,
    "2nd places": 5,
    "3rd places": 9,
    "Pole positions from '74 to 2022": 8,
    "Race fastest lap to 2022": 3,
    "World Championships": 1
  },
  {
    "Riders All Time in All Classes": "FOGGIA Dennis",
    "Victories": 7,
    "2nd places": 5,
    "3rd places": 6,
    "Pole positions from '74 to 2022": "",
    "Race fastest lap to 2022": 3,
    "World Championships": ""
  },
  {
    "Riders All Time in All Classes": "PASOLINI Renzo",
    "Victories": 6,
    "2nd places": 17,
    "3rd places": 12,
    "Pole positions from '74 to 2022": "",
    "Race fastest lap to 2022": 7,
    "World Championships": ""
  },
  {
    "Riders All Time in All Classes": "OKADA Tadayuki",
    "Victories": 6,
    "2nd places": 16,
    "3rd places": 14,
    "Pole positions from '74 to 2022": 7,
    "Race fastest lap to 2022": 8,
    "World Championships": ""
  },
  {
    "Riders All Time in All Classes": "CANET Aron",
    "Victories": 6,
    "2nd places": 10,
    "3rd places": 8,
    "Pole positions from '74 to 2022": 7,
    "Race fastest lap to 2022": 10,
    "World Championships": ""
  },
  {
    "Riders All Time in All Classes": "BEZZECCHI Marco",
    "Victories": 6,
    "2nd places": 9,
    "3rd places": 9,
    "Pole positions from '74 to 2022": 4,
    "Race fastest lap to 2022": 1,
    "World Championships": ""
  },
  {
    "Riders All Time in All Classes": "MASETTI Umberto",
    "Victories": 6,
    "2nd places": 9,
    "3rd places": 6,
    "Pole positions from '74 to 2022": "",
    "Race fastest lap to 2022": 1,
    "World Championships": 2
  },
  {
    "Riders All Time in All Classes": "MANAKO Tomomi",
    "Victories": 6,
    "2nd places": 8,
    "3rd places": 9,
    "Pole positions from '74 to 2022": "",
    "Race fastest lap to 2022": 7,
    "World Championships": ""
  },
  {
    "Riders All Time in All Classes": "GARDNER Remy",
    "Victories": 6,
    "2nd places": 8,
    "3rd places": 3,
    "Pole positions from '74 to 2022": 6,
    "Race fastest lap to 2022": 5,
    "World Championships": 1
  },
  {
    "Riders All Time in All Classes": "NAKANO Shinya",
    "Victories": 6,
    "2nd places": 7,
    "3rd places": 8,
    "Pole positions from '74 to 2022": 5,
    "Race fastest lap to 2022": 9,
    "World Championships": ""
  },
  {
    "Riders All Time in All Classes": "LUCCHINELLI Marco",
    "Victories": 6,
    "2nd places": 7,
    "3rd places": 6,
    "Pole positions from '74 to 2022": 9,
    "Race fastest lap to 2022": 9,
    "World Championships": 1
  },
  {
    "Riders All Time in All Classes": "GARCIA Sergio",
    "Victories": 6,
    "2nd places": 7,
    "3rd places": "",
    "Pole positions from '74 to 2022": 2,
    "Race fastest lap to 2022": 4,
    "World Championships": ""
  },
  {
    "Riders All Time in All Classes": "ROMBONI Doriano",
    "Victories": 6,
    "2nd places": 6,
    "3rd places": 10,
    "Pole positions from '74 to 2022": 7,
    "Race fastest lap to 2022": 4,
    "World Championships": ""
  },
  {
    "Riders All Time in All Classes": "PHILLIS Tom",
    "Victories": 6,
    "2nd places": 6,
    "3rd places": 8,
    "Pole positions from '74 to 2022": "",
    "Race fastest lap to 2022": 9,
    "World Championships": 1
  },
  {
    "Riders All Time in All Classes": "AMM Ray",
    "Victories": 6,
    "2nd places": 6,
    "3rd places": 4,
    "Pole positions from '74 to 2022": "",
    "Race fastest lap to 2022": 9,
    "World Championships": ""
  },
  {
    "Riders All Time in All Classes": "MARINI Luca",
    "Victories": 6,
    "2nd places": 6,
    "3rd places": 3,
    "Pole positions from '74 to 2022": 5,
    "Race fastest lap to 2022": 5,
    "World Championships": ""
  },
  {
    "Riders All Time in All Classes": "BERTIN Guy",
    "Victories": 6,
    "2nd places": 5,
    "3rd places": 1,
    "Pole positions from '74 to 2022": 8,
    "Race fastest lap to 2022": 8,
    "World Championships": ""
  },
  {
    "Riders All Time in All Classes": "LIBERATI Libero",
    "Victories": 6,
    "2nd places": 4,
    "3rd places": 4,
    "Pole positions from '74 to 2022": "",
    "Race fastest lap to 2022": 3,
    "World Championships": 1
  },
  {
    "Riders All Time in All Classes": "ARENAS Albert",
    "Victories": 6,
    "2nd places": 2,
    "3rd places": 2,
    "Pole positions from '74 to 2022": "",
    "Race fastest lap to 2022": 1,
    "World Championships": 1
  },
  {
    "Riders All Time in All Classes": "TOERSEN Aalt",
    "Victories": 6,
    "2nd places": 1,
    "3rd places": 6,
    "Pole positions from '74 to 2022": "",
    "Race fastest lap to 2022": 5,
    "World Championships": ""
  },
  {
    "Riders All Time in All Classes": "ACOSTA Pedro",
    "Victories": 6,
    "2nd places": 1,
    "3rd places": 1,
    "Pole positions from '74 to 2022": 1,
    "Race fastest lap to 2022": 1,
    "World Championships": 1
  },
  {
    "Riders All Time in All Classes": "HERWEH Manfred",
    "Victories": 6,
    "2nd places": "",
    "3rd places": 6,
    "Pole positions from '74 to 2022": 3,
    "Race fastest lap to 2022": 3,
    "World Championships": ""
  },
  {
    "Riders All Time in All Classes": "HARTLE John",
    "Victories": 5,
    "2nd places": 21,
    "3rd places": 8,
    "Pole positions from '74 to 2022": "",
    "Race fastest lap to 2022": 2,
    "World Championships": ""
  },
  {
    "Riders All Time in All Classes": "UKAWA Tohru",
    "Victories": 5,
    "2nd places": 17,
    "3rd places": 17,
    "Pole positions from '74 to 2022": 3,
    "Race fastest lap to 2022": 5,
    "World Championships": ""
  },
  {
    "Riders All Time in All Classes": "MCINTYRE Bob",
    "Victories": 5,
    "2nd places": 14,
    "3rd places": 6,
    "Pole positions from '74 to 2022": "",
    "Race fastest lap to 2022": 9,
    "World Championships": ""
  },
  {
    "Riders All Time in All Classes": "KNEUBÜHLER Bruno",
    "Victories": 5,
    "2nd places": 13,
    "3rd places": 15,
    "Pole positions from '74 to 2022": 5,
    "Race fastest lap to 2022": 4,
    "World Championships": ""
  },
  {
    "Riders All Time in All Classes": "CARDÚS Carlos",
    "Victories": 5,
    "2nd places": 12,
    "3rd places": 9,
    "Pole positions from '74 to 2022": 7,
    "Race fastest lap to 2022": 5,
    "World Championships": ""
  },
  {
    "Riders All Time in All Classes": "KAVANAGH Ken",
    "Victories": 5,
    "2nd places": 11,
    "3rd places": 8,
    "Pole positions from '74 to 2022": "",
    "Race fastest lap to 2022": 6,
    "World Championships": ""
  },
  {
    "Riders All Time in All Classes": "BALDÉ Jean Francois",
    "Victories": 5,
    "2nd places": 10,
    "3rd places": 11,
    "Pole positions from '74 to 2022": 7,
    "Race fastest lap to 2022": 4,
    "World Championships": ""
  },
  {
    "Riders All Time in All Classes": "DALLA PORTA Lorenzo",
    "Victories": 5,
    "2nd places": 9,
    "3rd places": 2,
    "Pole positions from '74 to 2022": 1,
    "Race fastest lap to 2022": 3,
    "World Championships": 1
  },
  {
    "Riders All Time in All Classes": "DE PUNIET Randy",
    "Victories": 5,
    "2nd places": 8,
    "3rd places": 11,
    "Pole positions from '74 to 2022": 9,
    "Race fastest lap to 2022": 4,
    "World Championships": ""
  },
  {
    "Riders All Time in All Classes": "BRADL Helmut",
    "Victories": 5,
    "2nd places": 8,
    "3rd places": 8,
    "Pole positions from '74 to 2022": 12,
    "Race fastest lap to 2022": 5,
    "World Championships": ""
  },
  {
    "Riders All Time in All Classes": "PERUGINI Stefano",
    "Victories": 5,
    "2nd places": 8,
    "3rd places": 6,
    "Pole positions from '74 to 2022": 5,
    "Race fastest lap to 2022": 8,
    "World Championships": ""
  },
  {
    "Riders All Time in All Classes": "FOLGER Jonas",
    "Victories": 5,
    "2nd places": 7,
    "3rd places": 12,
    "Pole positions from '74 to 2022": 6,
    "Race fastest lap to 2022": 8,
    "World Championships": ""
  },
  {
    "Riders All Time in All Classes": "OETTL Peter",
    "Victories": 5,
    "2nd places": 6,
    "3rd places": 9,
    "Pole positions from '74 to 2022": "",
    "Race fastest lap to 2022": 7,
    "World Championships": ""
  },
  {
    "Riders All Time in All Classes": "AUINGER August",
    "Victories": 5,
    "2nd places": 6,
    "3rd places": 7,
    "Pole positions from '74 to 2022": 3,
    "Race fastest lap to 2022": 7,
    "World Championships": ""
  },
  {
    "Riders All Time in All Classes": "DI MEGLIO Mike",
    "Victories": 5,
    "2nd places": 6,
    "3rd places": 2,
    "Pole positions from '74 to 2022": 3,
    "Race fastest lap to 2022": 4,
    "World Championships": 1
  },
  {
    "Riders All Time in All Classes": "SANDFORD Cecyl",
    "Victories": 5,
    "2nd places": 5,
    "3rd places": 11,
    "Pole positions from '74 to 2022": "",
    "Race fastest lap to 2022": 3,
    "World Championships": 2
  },
  {
    "Riders All Time in All Classes": "NIETO Fonsi",
    "Victories": 5,
    "2nd places": 5,
    "3rd places": 8,
    "Pole positions from '74 to 2022": 12,
    "Race fastest lap to 2022": 7,
    "World Championships": ""
  },
  {
    "Riders All Time in All Classes": "MASIA Jaume",
    "Victories": 5,
    "2nd places": 5,
    "3rd places": 3,
    "Pole positions from '74 to 2022": 4,
    "Race fastest lap to 2022": 11,
    "World Championships": ""
  },
  {
    "Riders All Time in All Classes": "BALDASSARRI Lorenzo",
    "Victories": 5,
    "2nd places": 5,
    "3rd places": 2,
    "Pole positions from '74 to 2022": 2,
    "Race fastest lap to 2022": 5,
    "World Championships": ""
  },
  {
    "Riders All Time in All Classes": "CORSI Simone",
    "Victories": 5,
    "2nd places": 4,
    "3rd places": 12,
    "Pole positions from '74 to 2022": 5,
    "Race fastest lap to 2022": 2,
    "World Championships": ""
  },
  {
    "Riders All Time in All Classes": "TOKUDOME Masaki",
    "Victories": 5,
    "2nd places": 3,
    "3rd places": 3,
    "Pole positions from '74 to 2022": 5,
    "Race fastest lap to 2022": 3,
    "World Championships": ""
  },
  {
    "Riders All Time in All Classes": "HARTOG Wil",
    "Victories": 5,
    "2nd places": 2,
    "3rd places": 5,
    "Pole positions from '74 to 2022": "",
    "Race fastest lap to 2022": 2,
    "World Championships": ""
  },
  {
    "Riders All Time in All Classes": "CHILI Pierfrancesco",
    "Victories": 5,
    "2nd places": 2,
    "3rd places": 4,
    "Pole positions from '74 to 2022": 5,
    "Race fastest lap to 2022": 4,
    "World Championships": ""
  },
  {
    "Riders All Time in All Classes": "FRITH Freddie",
    "Victories": 5,
    "2nd places": "",
    "3rd places": "",
    "Pole positions from '74 to 2022": "",
    "Race fastest lap to 2022": 5,
    "World Championships": 1
  },
  {
    "Riders All Time in All Classes": "DE ANGELIS Alex",
    "Victories": 4,
    "2nd places": 19,
    "3rd places": 17,
    "Pole positions from '74 to 2022": 11,
    "Race fastest lap to 2022": 18,
    "World Championships": ""
  },
  {
    "Riders All Time in All Classes": "ALZAMORA Emilio",
    "Victories": 4,
    "2nd places": 13,
    "3rd places": 13,
    "Pole positions from '74 to 2022": 1,
    "Race fastest lap to 2022": 5,
    "World Championships": 1
  },
  {
    "Riders All Time in All Classes": "ROLFO Roberto",
    "Victories": 4,
    "2nd places": 10,
    "3rd places": 6,
    "Pole positions from '74 to 2022": "",
    "Race fastest lap to 2022": 3,
    "World Championships": ""
  },
  {
    "Riders All Time in All Classes": "JANSSON Borje",
    "Victories": 4,
    "2nd places": 8,
    "3rd places": 13,
    "Pole positions from '74 to 2022": "",
    "Race fastest lap to 2022": 3,
    "World Championships": ""
  },
  {
    "Riders All Time in All Classes": "DE RADIGUES Didier",
    "Victories": 4,
    "2nd places": 8,
    "3rd places": 3,
    "Pole positions from '74 to 2022": 12,
    "Race fastest lap to 2022": 3,
    "World Championships": ""
  },
  {
    "Riders All Time in All Classes": "RITTBERGER Herbert",
    "Victories": 4,
    "2nd places": 8,
    "3rd places": 2,
    "Pole positions from '74 to 2022": 1,
    "Race fastest lap to 2022": "",
    "World Championships": ""
  },
  {
    "Riders All Time in All Classes": "DODDS John",
    "Victories": 4,
    "2nd places": 6,
    "3rd places": 11,
    "Pole positions from '74 to 2022": 3,
    "Race fastest lap to 2022": 4,
    "World Championships": ""
  },
  {
    "Riders All Time in All Classes": "REDDING Scott",
    "Victories": 4,
    "2nd places": 5,
    "3rd places": 9,
    "Pole positions from '74 to 2022": 3,
    "Race fastest lap to 2022": 5,
    "World Championships": ""
  },
  {
    "Riders All Time in All Classes": "ARBOLINO Tony",
    "Victories": 4,
    "2nd places": 5,
    "3rd places": 4,
    "Pole positions from '74 to 2022": 6,
    "Race fastest lap to 2022": 1,
    "World Championships": ""
  },
  {
    "Riders All Time in All Classes": "PARLOTTI Gilberto",
    "Victories": 4,
    "2nd places": 5,
    "3rd places": 3,
    "Pole positions from '74 to 2022": "",
    "Race fastest lap to 2022": 8,
    "World Championships": ""
  },
  {
    "Riders All Time in All Classes": "KATAYAMA Yoshimi",
    "Victories": 4,
    "2nd places": 5,
    "3rd places": 3,
    "Pole positions from '74 to 2022": "",
    "Race fastest lap to 2022": 6,
    "World Championships": ""
  },
  {
    "Riders All Time in All Classes": "RUFFO Bruno",
    "Victories": 4,
    "2nd places": 5,
    "3rd places": 1,
    "Pole positions from '74 to 2022": "",
    "Race fastest lap to 2022": 6,
    "World Championships": 3
  },
  {
    "Riders All Time in All Classes": "STASTNY Franta",
    "Victories": 4,
    "2nd places": 4,
    "3rd places": 12,
    "Pole positions from '74 to 2022": "",
    "Race fastest lap to 2022": 1,
    "World Championships": ""
  },
  {
    "Riders All Time in All Classes": "SARRON Dominique",
    "Victories": 4,
    "2nd places": 4,
    "3rd places": 8,
    "Pole positions from '74 to 2022": 7,
    "Race fastest lap to 2022": 3,
    "World Championships": ""
  },
  {
    "Riders All Time in All Classes": "HERRERO Santiago",
    "Victories": 4,
    "2nd places": 4,
    "3rd places": 3,
    "Pole positions from '74 to 2022": "",
    "Race fastest lap to 2022": 3,
    "World Championships": ""
  },
  {
    "Riders All Time in All Classes": "TAKAHASHI Kuninitsu",
    "Victories": 4,
    "2nd places": 3,
    "3rd places": 7,
    "Pole positions from '74 to 2022": "",
    "Race fastest lap to 2022": 3,
    "World Championships": ""
  },
  {
    "Riders All Time in All Classes": "VIETTI Celestino",
    "Victories": 4,
    "2nd places": 3,
    "3rd places": 5,
    "Pole positions from '74 to 2022": 2,
    "Race fastest lap to 2022": 4,
    "World Championships": ""
  },
  {
    "Riders All Time in All Classes": "ANTONELLI Niccolò",
    "Victories": 4,
    "2nd places": 3,
    "3rd places": 4,
    "Pole positions from '74 to 2022": 9,
    "Race fastest lap to 2022": 4,
    "World Championships": ""
  },
  {
    "Riders All Time in All Classes": "PAGANI Nello",
    "Victories": 4,
    "2nd places": 2,
    "3rd places": 5,
    "Pole positions from '74 to 2022": "",
    "Race fastest lap to 2022": 4,
    "World Championships": 1
  },
  {
    "Riders All Time in All Classes": "WAIBEL Gerhard",
    "Victories": 4,
    "2nd places": 2,
    "3rd places": 5,
    "Pole positions from '74 to 2022": 1,
    "Race fastest lap to 2022": "",
    "World Championships": ""
  },
  {
    "Riders All Time in All Classes": "SMITH Barry",
    "Victories": 4,
    "2nd places": 2,
    "3rd places": 4,
    "Pole positions from '74 to 2022": "",
    "Race fastest lap to 2022": 2,
    "World Championships": ""
  },
  {
    "Riders All Time in All Classes": "LODEWIJKX Paul",
    "Victories": 4,
    "2nd places": 1,
    "3rd places": 1,
    "Pole positions from '74 to 2022": "",
    "Race fastest lap to 2022": 2,
    "World Championships": ""
  },
  {
    "Riders All Time in All Classes": "DRAPAL Janos",
    "Victories": 4,
    "2nd places": "",
    "3rd places": 1,
    "Pole positions from '74 to 2022": "",
    "Race fastest lap to 2022": 2,
    "World Championships": ""
  },
  {
    "Riders All Time in All Classes": "SMITH Bradley",
    "Victories": 3,
    "2nd places": 10,
    "3rd places": 12,
    "Pole positions from '74 to 2022": 9,
    "Race fastest lap to 2022": 5,
    "World Championships": ""
  },
  {
    "Riders All Time in All Classes": "DI GIANNANTONIO Fabio",
    "Victories": 3,
    "2nd places": 10,
    "3rd places": 9,
    "Pole positions from '74 to 2022": 1,
    "Race fastest lap to 2022": 3,
    "World Championships": ""
  },
  {
    "Riders All Time in All Classes": "FINDLAY Jack",
    "Victories": 3,
    "2nd places": 9,
    "3rd places": 13,
    "Pole positions from '74 to 2022": 1,
    "Race fastest lap to 2022": 1,
    "World Championships": ""
  },
  {
    "Riders All Time in All Classes": "DUFF Mike",
    "Victories": 3,
    "2nd places": 9,
    "3rd places": 12,
    "Pole positions from '74 to 2022": "",
    "Race fastest lap to 2022": 5,
    "World Championships": ""
  },
  {
    "Riders All Time in All Classes": "PERRIS Frank",
    "Victories": 3,
    "2nd places": 8,
    "3rd places": 7,
    "Pole positions from '74 to 2022": "",
    "Race fastest lap to 2022": 2,
    "World Championships": ""
  },
  {
    "Riders All Time in All Classes": "ROTH Reinhold",
    "Victories": 3,
    "2nd places": 8,
    "3rd places": 4,
    "Pole positions from '74 to 2022": 2,
    "Race fastest lap to 2022": 3,
    "World Championships": ""
  },
  {
    "Riders All Time in All Classes": "ROBB Tommy",
    "Victories": 3,
    "2nd places": 7,
    "3rd places": 18,
    "Pole positions from '74 to 2022": "",
    "Race fastest lap to 2022": 2,
    "World Championships": ""
  },
  {
    "Riders All Time in All Classes": "CORNU Jacques",
    "Victories": 3,
    "2nd places": 7,
    "3rd places": 11,
    "Pole positions from '74 to 2022": 3,
    "Race fastest lap to 2022": 3,
    "World Championships": ""
  },
  {
    "Riders All Time in All Classes": "GRASSETTI Silvio",
    "Victories": 3,
    "2nd places": 7,
    "3rd places": 11,
    "Pole positions from '74 to 2022": "",
    "Race fastest lap to 2022": 3,
    "World Championships": ""
  },
  {
    "Riders All Time in All Classes": "PAGANI Alberto",
    "Victories": 3,
    "2nd places": 7,
    "3rd places": 9,
    "Pole positions from '74 to 2022": "",
    "Race fastest lap to 2022": "",
    "World Championships": ""
  },
  {
    "Riders All Time in All Classes": "ROUGERIE Michel",
    "Victories": 3,
    "2nd places": 7,
    "3rd places": 7,
    "Pole positions from '74 to 2022": 6,
    "Race fastest lap to 2022": 2,
    "World Championships": ""
  },
  {
    "Riders All Time in All Classes": "BEATTIE Daryl",
    "Victories": 3,
    "2nd places": 7,
    "3rd places": 4,
    "Pole positions from '74 to 2022": "",
    "Race fastest lap to 2022": 1,
    "World Championships": ""
  },
  {
    "Riders All Time in All Classes": "HAYDEN Nicky",
    "Victories": 3,
    "2nd places": 6,
    "3rd places": 19,
    "Pole positions from '74 to 2022": 5,
    "Race fastest lap to 2022": 7,
    "World Championships": 1
  },
  {
    "Riders All Time in All Classes": "FERNANDEZ Patrick",
    "Victories": 3,
    "2nd places": 6,
    "3rd places": 17,
    "Pole positions from '74 to 2022": 4,
    "Race fastest lap to 2022": 1,
    "World Championships": ""
  },
  {
    "Riders All Time in All Classes": "CRUTCHLOW Cal",
    "Victories": 3,
    "2nd places": 6,
    "3rd places": 10,
    "Pole positions from '74 to 2022": 4,
    "Race fastest lap to 2022": 4,
    "World Championships": ""
  },
  {
    "Riders All Time in All Classes": "GADEA Sergio",
    "Victories": 3,
    "2nd places": 6,
    "3rd places": 9,
    "Pole positions from '74 to 2022": 2,
    "Race fastest lap to 2022": 6,
    "World Championships": ""
  },
  {
    "Riders All Time in All Classes": "WIMMER Martin",
    "Victories": 3,
    "2nd places": 6,
    "3rd places": 7,
    "Pole positions from '74 to 2022": 8,
    "Race fastest lap to 2022": 8,
    "World Championships": ""
  },
  {
    "Riders All Time in All Classes": "MCPHEE John",
    "Victories": 3,
    "2nd places": 6,
    "3rd places": 6,
    "Pole positions from '74 to 2022": 5,
    "Race fastest lap to 2022": 2,
    "World Championships": ""
  },
  {
    "Riders All Time in All Classes": "KANAYA Hideo",
    "Victories": 3,
    "2nd places": 6,
    "3rd places": 6,
    "Pole positions from '74 to 2022": 2,
    "Race fastest lap to 2022": 4,
    "World Championships": ""
  },
  {
    "Riders All Time in All Classes": "BUSCHERINI Otello",
    "Victories": 3,
    "2nd places": 5,
    "3rd places": 9,
    "Pole positions from '74 to 2022": 4,
    "Race fastest lap to 2022": 8,
    "World Championships": ""
  },
  {
    "Riders All Time in All Classes": "HENNEN Pat",
    "Victories": 3,
    "2nd places": 5,
    "3rd places": 4,
    "Pole positions from '74 to 2022": "",
    "Race fastest lap to 2022": "",
    "World Championships": ""
  },
  {
    "Riders All Time in All Classes": "ABE Norick",
    "Victories": 3,
    "2nd places": 4,
    "3rd places": 10,
    "Pole positions from '74 to 2022": "",
    "Race fastest lap to 2022": 1,
    "World Championships": ""
  },
  {
    "Riders All Time in All Classes": "GARRIGA Juan",
    "Victories": 3,
    "2nd places": 4,
    "3rd places": 6,
    "Pole positions from '74 to 2022": 2,
    "Race fastest lap to 2022": 11,
    "World Championships": ""
  },
  {
    "Riders All Time in All Classes": "TIMMER Theo",
    "Victories": 3,
    "2nd places": 4,
    "3rd places": 5,
    "Pole positions from '74 to 2022": "",
    "Race fastest lap to 2022": "",
    "World Championships": ""
  },
  {
    "Riders All Time in All Classes": "TAKAHASHI Yuki",
    "Victories": 3,
    "2nd places": 4,
    "3rd places": 4,
    "Pole positions from '74 to 2022": "",
    "Race fastest lap to 2022": "",
    "World Championships": ""
  },
  {
    "Riders All Time in All Classes": "MILANI Alfredo",
    "Victories": 3,
    "2nd places": 4,
    "3rd places": 2,
    "Pole positions from '74 to 2022": "",
    "Race fastest lap to 2022": 3,
    "World Championships": ""
  },
  {
    "Riders All Time in All Classes": "GRAMIGNI Alessandro",
    "Victories": 3,
    "2nd places": 3,
    "3rd places": 6,
    "Pole positions from '74 to 2022": 3,
    "Race fastest lap to 2022": "",
    "World Championships": 1
  },
  {
    "Riders All Time in All Classes": "RUGGIA Jean Philippe",
    "Victories": 3,
    "2nd places": 3,
    "3rd places": 4,
    "Pole positions from '74 to 2022": 2,
    "Race fastest lap to 2022": 2,
    "World Championships": ""
  },
  {
    "Riders All Time in All Classes": "GRANT Mike",
    "Victories": 3,
    "2nd places": 3,
    "3rd places": 3,
    "Pole positions from '74 to 2022": 1,
    "Race fastest lap to 2022": 4,
    "World Championships": ""
  },
  {
    "Riders All Time in All Classes": "MENDOGNI Emilio",
    "Victories": 3,
    "2nd places": 3,
    "3rd places": 3,
    "Pole positions from '74 to 2022": "",
    "Race fastest lap to 2022": 2,
    "World Championships": ""
  },
  {
    "Riders All Time in All Classes": "SANNA Simone",
    "Victories": 3,
    "2nd places": 3,
    "3rd places": 3,
    "Pole positions from '74 to 2022": "",
    "Race fastest lap to 2022": 1,
    "World Championships": ""
  },
  {
    "Riders All Time in All Classes": "ROSSI Graziano",
    "Victories": 3,
    "2nd places": 2,
    "3rd places": 2,
    "Pole positions from '74 to 2022": 1,
    "Race fastest lap to 2022": "",
    "World Championships": ""
  },
  {
    "Riders All Time in All Classes": "WILLIAMS Charlie",
    "Victories": 3,
    "2nd places": 2,
    "3rd places": "",
    "Pole positions from '74 to 2022": "",
    "Race fastest lap to 2022": 2,
    "World Championships": ""
  },
  {
    "Riders All Time in All Classes": "CANN Maurice",
    "Victories": 3,
    "2nd places": 2,
    "3rd places": "",
    "Pole positions from '74 to 2022": "",
    "Race fastest lap to 2022": 2,
    "World Championships": ""
  },
  {
    "Riders All Time in All Classes": "FERNANDEZ Augusto",
    "Victories": 3,
    "2nd places": 1,
    "3rd places": 7,
    "Pole positions from '74 to 2022": 1,
    "Race fastest lap to 2022": 6,
    "World Championships": ""
  },
  {
    "Riders All Time in All Classes": "CHECA Carlos",
    "Victories": 2,
    "2nd places": 14,
    "3rd places": 8,
    "Pole positions from '74 to 2022": 3,
    "Race fastest lap to 2022": 5,
    "World Championships": ""
  },
  {
    "Riders All Time in All Classes": "HERREROS Manuel",
    "Victories": 2,
    "2nd places": 12,
    "3rd places": 8,
    "Pole positions from '74 to 2022": "",
    "Race fastest lap to 2022": "",
    "World Championships": 1
  },
  {
    "Riders All Time in All Classes": "SHEPHERD Alan",
    "Victories": 2,
    "2nd places": 9,
    "3rd places": 9,
    "Pole positions from '74 to 2022": "",
    "Race fastest lap to 2022": 3,
    "World Championships": ""
  },
  {
    "Riders All Time in All Classes": "NAVARRO Jorge",
    "Victories": 2,
    "2nd places": 8,
    "3rd places": 9,
    "Pole positions from '74 to 2022": 5,
    "Race fastest lap to 2022": 4,
    "World Championships": ""
  },
  {
    "Riders All Time in All Classes": "BONERA Gianfranco",
    "Victories": 2,
    "2nd places": 7,
    "3rd places": 6,
    "Pole positions from '74 to 2022": 1,
    "Race fastest lap to 2022": 4,
    "World Championships": ""
  },
  {
    "Riders All Time in All Classes": "GRAHAM Stuart",
    "Victories": 2,
    "2nd places": 7,
    "3rd places": 5,
    "Pole positions from '74 to 2022": "",
    "Race fastest lap to 2022": 1,
    "World Championships": ""
  },
  {
    "Riders All Time in All Classes": "VAZQUEZ Efren",
    "Victories": 2,
    "2nd places": 6,
    "3rd places": 8,
    "Pole positions from '74 to 2022": 1,
    "Race fastest lap to 2022": 4,
    "World Championships": ""
  },
  {
    "Riders All Time in All Classes": "FERRARI Virginio",
    "Victories": 2,
    "2nd places": 6,
    "3rd places": 2,
    "Pole positions from '74 to 2022": 1,
    "Race fastest lap to 2022": 3,
    "World Championships": ""
  },
  {
    "Riders All Time in All Classes": "DALE Dickie",
    "Victories": 2,
    "2nd places": 5,
    "3rd places": 5,
    "Pole positions from '74 to 2022": "",
    "Race fastest lap to 2022": 2,
    "World Championships": ""
  },
  {
    "Riders All Time in All Classes": "BERGAMONTI Angelo",
    "Victories": 2,
    "2nd places": 5,
    "3rd places": 3,
    "Pole positions from '74 to 2022": "",
    "Race fastest lap to 2022": 2,
    "World Championships": ""
  },
  {
    "Riders All Time in All Classes": "NAKAGAMI Takaaki",
    "Victories": 2,
    "2nd places": 4,
    "3rd places": 8,
    "Pole positions from '74 to 2022": 6,
    "Race fastest lap to 2022": 1,
    "World Championships": ""
  },
  {
    "Riders All Time in All Classes": "HERRON Tom",
    "Victories": 2,
    "2nd places": 4,
    "3rd places": 8,
    "Pole positions from '74 to 2022": 3,
    "Race fastest lap to 2022": 1,
    "World Championships": ""
  },
  {
    "Riders All Time in All Classes": "PETRUCCI Danilo",
    "Victories": 2,
    "2nd places": 4,
    "3rd places": 4,
    "Pole positions from '74 to 2022": "",
    "Race fastest lap to 2022": 2,
    "World Championships": ""
  },
  {
    "Riders All Time in All Classes": "PALAZZESE Ivan",
    "Victories": 2,
    "2nd places": 4,
    "3rd places": 3,
    "Pole positions from '74 to 2022": 1,
    "Race fastest lap to 2022": 2,
    "World Championships": ""
  },
  {
    "Riders All Time in All Classes": "ITOH Mitsuo",
    "Victories": 2,
    "2nd places": 3,
    "3rd places": 8,
    "Pole positions from '74 to 2022": "",
    "Race fastest lap to 2022": 1,
    "World Championships": ""
  },
  {
    "Riders All Time in All Classes": "MIGNO Andrea",
    "Victories": 2,
    "2nd places": 3,
    "3rd places": 6,
    "Pole positions from '74 to 2022": 4,
    "Race fastest lap to 2022": 4,
    "World Championships": ""
  },
  {
    "Riders All Time in All Classes": "PESEK Lukas",
    "Victories": 2,
    "2nd places": 3,
    "3rd places": 4,
    "Pole positions from '74 to 2022": 3,
    "Race fastest lap to 2022": 4,
    "World Championships": ""
  },
  {
    "Riders All Time in All Classes": "DORAN William",
    "Victories": 2,
    "2nd places": 3,
    "3rd places": 3,
    "Pole positions from '74 to 2022": "",
    "Race fastest lap to 2022": 2,
    "World Championships": ""
  },
  {
    "Riders All Time in All Classes": "DEBON Alex",
    "Victories": 2,
    "2nd places": 3,
    "3rd places": 2,
    "Pole positions from '74 to 2022": 4,
    "Race fastest lap to 2022": 3,
    "World Championships": ""
  },
  {
    "Riders All Time in All Classes": "WOOD Tommy",
    "Victories": 2,
    "2nd places": 3,
    "3rd places": 1,
    "Pole positions from '74 to 2022": "",
    "Race fastest lap to 2022": 2,
    "World Championships": ""
  },
  {
    "Riders All Time in All Classes": "RAMIREZ Marcos",
    "Victories": 2,
    "2nd places": 2,
    "3rd places": 4,
    "Pole positions from '74 to 2022": 2,
    "Race fastest lap to 2022": 2,
    "World Championships": ""
  },
  {
    "Riders All Time in All Classes": "SAUL Eric",
    "Victories": 2,
    "2nd places": 2,
    "3rd places": 4,
    "Pole positions from '74 to 2022": 1,
    "Race fastest lap to 2022": 1,
    "World Championships": ""
  },
  {
    "Riders All Time in All Classes": "MONNERET Pierre",
    "Victories": 2,
    "2nd places": 2,
    "3rd places": 4,
    "Pole positions from '74 to 2022": "",
    "Race fastest lap to 2022": 2,
    "World Championships": ""
  },
  {
    "Riders All Time in All Classes": "VITALI Maurizio",
    "Victories": 2,
    "2nd places": 2,
    "3rd places": 3,
    "Pole positions from '74 to 2022": 5,
    "Race fastest lap to 2022": 1,
    "World Championships": ""
  },
  {
    "Riders All Time in All Classes": "WEST Anthony",
    "Victories": 2,
    "2nd places": 2,
    "3rd places": 2,
    "Pole positions from '74 to 2022": "",
    "Race fastest lap to 2022": 1,
    "World Championships": ""
  },
  {
    "Riders All Time in All Classes": "RUTTER Tony",
    "Victories": 2,
    "2nd places": 2,
    "3rd places": 1,
    "Pole positions from '74 to 2022": 2,
    "Race fastest lap to 2022": 1,
    "World Championships": ""
  },
  {
    "Riders All Time in All Classes": "TAMADA Makoto",
    "Victories": 2,
    "2nd places": 1,
    "3rd places": 2,
    "Pole positions from '74 to 2022": 3,
    "Race fastest lap to 2022": 2,
    "World Championships": ""
  },
  {
    "Riders All Time in All Classes": "SCALVINI Gianluigi",
    "Victories": 2,
    "2nd places": 1,
    "3rd places": 2,
    "Pole positions from '74 to 2022": 2,
    "Race fastest lap to 2022": 2,
    "World Championships": ""
  },
  {
    "Riders All Time in All Classes": "HUBERTS Jan",
    "Victories": 2,
    "2nd places": 1,
    "3rd places": 2,
    "Pole positions from '74 to 2022": "",
    "Race fastest lap to 2022": 3,
    "World Championships": ""
  },
  {
    "Riders All Time in All Classes": "CAÑELLAS Salvador",
    "Victories": 2,
    "2nd places": 1,
    "3rd places": 2,
    "Pole positions from '74 to 2022": "",
    "Race fastest lap to 2022": 1,
    "World Championships": ""
  },
  {
    "Riders All Time in All Classes": "SUZUKI Tatsuki",
    "Victories": 2,
    "2nd places": 1,
    "3rd places": 1,
    "Pole positions from '74 to 2022": 6,
    "Race fastest lap to 2022": 3,
    "World Championships": ""
  },
  {
    "Riders All Time in All Classes": "MIDDELBURG Jack",
    "Victories": 2,
    "2nd places": 1,
    "3rd places": 1,
    "Pole positions from '74 to 2022": 2,
    "Race fastest lap to 2022": 1,
    "World Championships": ""
  },
  {
    "Riders All Time in All Classes": "MASBOU Alexis",
    "Victories": 2,
    "2nd places": 1,
    "3rd places": 1,
    "Pole positions from '74 to 2022": 1,
    "Race fastest lap to 2022": 1,
    "World Championships": ""
  },
  {
    "Riders All Time in All Classes": "GANDOSSI Alberto",
    "Victories": 2,
    "2nd places": 1,
    "3rd places": 1,
    "Pole positions from '74 to 2022": "",
    "Race fastest lap to 2022": 2,
    "World Championships": ""
  },
  {
    "Riders All Time in All Classes": "TORRONTEGUI Herri",
    "Victories": 2,
    "2nd places": "",
    "3rd places": 4,
    "Pole positions from '74 to 2022": "",
    "Race fastest lap to 2022": 1,
    "World Championships": ""
  },
  {
    "Riders All Time in All Classes": "WHEELER Arthur",
    "Victories": 2,
    "2nd places": "",
    "3rd places": 2,
    "Pole positions from '74 to 2022": "",
    "Race fastest lap to 2022": 2,
    "World Championships": ""
  },
  {
    "Riders All Time in All Classes": "MCCANDLESS Cromie",
    "Victories": 2,
    "2nd places": "",
    "3rd places": 1,
    "Pole positions from '74 to 2022": "",
    "Race fastest lap to 2022": 1,
    "World Championships": ""
  },
  {
    "Riders All Time in All Classes": "PAWI Khairul Idham",
    "Victories": 2,
    "2nd places": "",
    "3rd places": "",
    "Pole positions from '74 to 2022": "",
    "Race fastest lap to 2022": 1,
    "World Championships": ""
  },
  {
    "Riders All Time in All Classes": "KASSNER Helmut",
    "Victories": 2,
    "2nd places": "",
    "3rd places": "",
    "Pole positions from '74 to 2022": "",
    "Race fastest lap to 2022": 1,
    "World Championships": ""
  },
  {
    "Riders All Time in All Classes": "VENTURI Remo",
    "Victories": 1,
    "2nd places": 14,
    "3rd places": 7,
    "Pole positions from '74 to 2022": "",
    "Race fastest lap to 2022": 3,
    "World Championships": ""
  },
  {
    "Riders All Time in All Classes": "CASANOVA Bruno",
    "Victories": 1,
    "2nd places": 9,
    "3rd places": 6,
    "Pole positions from '74 to 2022": 6,
    "Race fastest lap to 2022": 5,
    "World Championships": ""
  },
  {
    "Riders All Time in All Classes": "MOLLOY Ginger",
    "Victories": 1,
    "2nd places": 9,
    "3rd places": 3,
    "Pole positions from '74 to 2022": "",
    "Race fastest lap to 2022": "",
    "World Championships": ""
  },
  {
    "Riders All Time in All Classes": "WILLIAMS Peter",
    "Victories": 1,
    "2nd places": 8,
    "3rd places": 2,
    "Pole positions from '74 to 2022": 1,
    "Race fastest lap to 2022": 2,
    "World Championships": ""
  },
  {
    "Riders All Time in All Classes": "FREYMOND Roland",
    "Victories": 1,
    "2nd places": 6,
    "3rd places": 3,
    "Pole positions from '74 to 2022": "",
    "Race fastest lap to 2022": 1,
    "World Championships": ""
  },
  {
    "Riders All Time in All Classes": "FERRI Romolo",
    "Victories": 1,
    "2nd places": 6,
    "3rd places": "",
    "Pole positions from '74 to 2022": "",
    "Race fastest lap to 2022": 4,
    "World Championships": ""
  },
  {
    "Riders All Time in All Classes": "KOYAMA Tomoyoshi",
    "Victories": 1,
    "2nd places": 5,
    "3rd places": 3,
    "Pole positions from '74 to 2022": "",
    "Race fastest lap to 2022": "",
    "World Championships": ""
  },
  {
    "Riders All Time in All Classes": "BRETT Jack",
    "Victories": 1,
    "2nd places": 4,
    "3rd places": 6,
    "Pole positions from '74 to 2022": "",
    "Race fastest lap to 2022": 1,
    "World Championships": ""
  },
  {
    "Riders All Time in All Classes": "COLEMAN Rod",
    "Victories": 1,
    "2nd places": 4,
    "3rd places": 6,
    "Pole positions from '74 to 2022": "",
    "Race fastest lap to 2022": 1,
    "World Championships": ""
  },
  {
    "Riders All Time in All Classes": "SCHURGERS Jos",
    "Victories": 1,
    "2nd places": 4,
    "3rd places": 6,
    "Pole positions from '74 to 2022": "",
    "Race fastest lap to 2022": "",
    "World Championships": ""
  },
  {
    "Riders All Time in All Classes": "TOURNADRE Jean Louis",
    "Victories": 1,
    "2nd places": 4,
    "3rd places": 4,
    "Pole positions from '74 to 2022": "",
    "Race fastest lap to 2022": 2,
    "World Championships": 1
  },
  {
    "Riders All Time in All Classes": "LEGA Mario",
    "Victories": 1,
    "2nd places": 4,
    "3rd places": 4,
    "Pole positions from '74 to 2022": "",
    "Race fastest lap to 2022": 1,
    "World Championships": 1
  },
  {
    "Riders All Time in All Classes": "BRIGAGLIA Domenico",
    "Victories": 1,
    "2nd places": 4,
    "3rd places": 4,
    "Pole positions from '74 to 2022": 1,
    "Race fastest lap to 2022": 2,
    "World Championships": ""
  },
  {
    "Riders All Time in All Classes": "GRAF Ulrich",
    "Victories": 1,
    "2nd places": 4,
    "3rd places": 4,
    "Pole positions from '74 to 2022": 1,
    "Race fastest lap to 2022": "",
    "World Championships": ""
  },
  {
    "Riders All Time in All Classes": "PREIN Stefan",
    "Victories": 1,
    "2nd places": 3,
    "3rd places": 4,
    "Pole positions from '74 to 2022": 2,
    "Race fastest lap to 2022": 5,
    "World Championships": ""
  },
  {
    "Riders All Time in All Classes": "MINTER Derek",
    "Victories": 1,
    "2nd places": 3,
    "3rd places": 4,
    "Pole positions from '74 to 2022": "",
    "Race fastest lap to 2022": "",
    "World Championships": ""
  },
  {
    "Riders All Time in All Classes": "VERMEULEN Chris",
    "Victories": 1,
    "2nd places": 3,
    "3rd places": 3,
    "Pole positions from '74 to 2022": 3,
    "Race fastest lap to 2022": 1,
    "World Championships": ""
  },
  {
    "Riders All Time in All Classes": "BINDER Darryn",
    "Victories": 1,
    "2nd places": 3,
    "3rd places": 2,
    "Pole positions from '74 to 2022": 3,
    "Race fastest lap to 2022": 6,
    "World Championships": ""
  },
  {
    "Riders All Time in All Classes": "BELL Artie",
    "Victories": 1,
    "2nd places": 3,
    "3rd places": 1,
    "Pole positions from '74 to 2022": "",
    "Race fastest lap to 2022": 1,
    "World Championships": ""
  },
  {
    "Riders All Time in All Classes": "ITO Fumio",
    "Victories": 1,
    "2nd places": 3,
    "3rd places": "",
    "Pole positions from '74 to 2022": "",
    "Race fastest lap to 2022": 2,
    "World Championships": ""
  },
  {
    "Riders All Time in All Classes": "KORHONEN Pentti",
    "Victories": 1,
    "2nd places": 2,
    "3rd places": 7,
    "Pole positions from '74 to 2022": 1,
    "Race fastest lap to 2022": "",
    "World Championships": ""
  },
  {
    "Riders All Time in All Classes": "WILLIAMS John",
    "Victories": 1,
    "2nd places": 2,
    "3rd places": 5,
    "Pole positions from '74 to 2022": "",
    "Race fastest lap to 2022": 1,
    "World Championships": ""
  },
  {
    "Riders All Time in All Classes": "SCHNEIDER Bert",
    "Victories": 1,
    "2nd places": 2,
    "3rd places": 5,
    "Pole positions from '74 to 2022": "",
    "Race fastest lap to 2022": "",
    "World Championships": ""
  },
  {
    "Riders All Time in All Classes": "MARSOVSZKY Gyula",
    "Victories": 1,
    "2nd places": 2,
    "3rd places": 5,
    "Pole positions from '74 to 2022": "",
    "Race fastest lap to 2022": "",
    "World Championships": ""
  },
  {
    "Riders All Time in All Classes": "AOKI Nobuatsu",
    "Victories": 1,
    "2nd places": 2,
    "3rd places": 4,
    "Pole positions from '74 to 2022": 1,
    "Race fastest lap to 2022": 1,
    "World Championships": ""
  },
  {
    "Riders All Time in All Classes": "CHEVALLIER Olivier",
    "Victories": 1,
    "2nd places": 2,
    "3rd places": 4,
    "Pole positions from '74 to 2022": 1,
    "Race fastest lap to 2022": "",
    "World Championships": ""
  },
  {
    "Riders All Time in All Classes": "MCCONNACHIE Ian",
    "Victories": 1,
    "2nd places": 2,
    "3rd places": 4,
    "Pole positions from '74 to 2022": 1,
    "Race fastest lap to 2022": "",
    "World Championships": ""
  },
  {
    "Riders All Time in All Classes": "SPIES Ben",
    "Victories": 1,
    "2nd places": 2,
    "3rd places": 3,
    "Pole positions from '74 to 2022": 1,
    "Race fastest lap to 2022": 1,
    "World Championships": ""
  },
  {
    "Riders All Time in All Classes": "NORTH Alan",
    "Victories": 1,
    "2nd places": 2,
    "3rd places": 2,
    "Pole positions from '74 to 2022": 6,
    "Race fastest lap to 2022": 1,
    "World Championships": ""
  },
  {
    "Riders All Time in All Classes": "LUCCHI Marcellino",
    "Victories": 1,
    "2nd places": 2,
    "3rd places": 2,
    "Pole positions from '74 to 2022": 3,
    "Race fastest lap to 2022": 1,
    "World Championships": ""
  },
  {
    "Riders All Time in All Classes": "SELINI Jean Claude",
    "Victories": 1,
    "2nd places": 2,
    "3rd places": 2,
    "Pole positions from '74 to 2022": 2,
    "Race fastest lap to 2022": 1,
    "World Championships": ""
  },
  {
    "Riders All Time in All Classes": "BOLLE Jacques",
    "Victories": 1,
    "2nd places": 2,
    "3rd places": 2,
    "Pole positions from '74 to 2022": 1,
    "Race fastest lap to 2022": 1,
    "World Championships": ""
  },
  {
    "Riders All Time in All Classes": "SIMEON Xavier",
    "Victories": 1,
    "2nd places": 2,
    "3rd places": 1,
    "Pole positions from '74 to 2022": 2,
    "Race fastest lap to 2022": 1,
    "World Championships": ""
  },
  {
    "Riders All Time in All Classes": "VAN DULMEN Boet",
    "Victories": 1,
    "2nd places": 2,
    "3rd places": 1,
    "Pole positions from '74 to 2022": 1,
    "Race fastest lap to 2022": "",
    "World Championships": ""
  },
  {
    "Riders All Time in All Classes": "SPAGGIARI Bruno",
    "Victories": 1,
    "2nd places": 2,
    "3rd places": 1,
    "Pole positions from '74 to 2022": "",
    "Race fastest lap to 2022": 1,
    "World Championships": ""
  },
  {
    "Riders All Time in All Classes": "KISSLING Jorge",
    "Victories": 1,
    "2nd places": 2,
    "3rd places": "",
    "Pole positions from '74 to 2022": "",
    "Race fastest lap to 2022": "",
    "World Championships": ""
  },
  {
    "Riders All Time in All Classes": "ZEELENBERG Wilco",
    "Victories": 1,
    "2nd places": 1,
    "3rd places": 9,
    "Pole positions from '74 to 2022": 1,
    "Race fastest lap to 2022": 1,
    "World Championships": ""
  },
  {
    "Riders All Time in All Classes": "PUIG Alberto",
    "Victories": 1,
    "2nd places": 1,
    "3rd places": 7,
    "Pole positions from '74 to 2022": "",
    "Race fastest lap to 2022": 1,
    "World Championships": ""
  },
  {
    "Riders All Time in All Classes": "NIETO Pablo",
    "Victories": 1,
    "2nd places": 1,
    "3rd places": 6,
    "Pole positions from '74 to 2022": 3,
    "Race fastest lap to 2022": 5,
    "World Championships": ""
  },
  {
    "Riders All Time in All Classes": "AHEARN Jack",
    "Victories": 1,
    "2nd places": 1,
    "3rd places": 6,
    "Pole positions from '74 to 2022": "",
    "Race fastest lap to 2022": "",
    "World Championships": ""
  },
  {
    "Riders All Time in All Classes": "AEGERTER Dominique",
    "Victories": 1,
    "2nd places": 1,
    "3rd places": 5,
    "Pole positions from '74 to 2022": 1,
    "Race fastest lap to 2022": 1,
    "World Championships": ""
  },
  {
    "Riders All Time in All Classes": "MCWILLIAMS Jeremy",
    "Victories": 1,
    "2nd places": 1,
    "3rd places": 4,
    "Pole positions from '74 to 2022": 3,
    "Race fastest lap to 2022": "",
    "World Championships": ""
  },
  {
    "Riders All Time in All Classes": "NEWCOMBE Kim",
    "Victories": 1,
    "2nd places": 1,
    "3rd places": 4,
    "Pole positions from '74 to 2022": "",
    "Race fastest lap to 2022": 1,
    "World Championships": ""
  },
  {
    "Riders All Time in All Classes": "ESPARGARO Aleix",
    "Victories": 1,
    "2nd places": 1,
    "3rd places": 3,
    "Pole positions from '74 to 2022": 3,
    "Race fastest lap to 2022": 1,
    "World Championships": ""
  },
  {
    "Riders All Time in All Classes": "CALDARELLA Benedicto",
    "Victories": 1,
    "2nd places": 1,
    "3rd places": 2,
    "Pole positions from '74 to 2022": "",
    "Race fastest lap to 2022": 2,
    "World Championships": ""
  },
  {
    "Riders All Time in All Classes": "TOBA Kaito",
    "Victories": 1,
    "2nd places": 1,
    "3rd places": 2,
    "Pole positions from '74 to 2022": "",
    "Race fastest lap to 2022": 1,
    "World Championships": ""
  },
  {
    "Riders All Time in All Classes": "TANAKA Kenjiro",
    "Victories": 1,
    "2nd places": 1,
    "3rd places": 2,
    "Pole positions from '74 to 2022": "",
    "Race fastest lap to 2022": "",
    "World Championships": ""
  },
  {
    "Riders All Time in All Classes": "CONFORTI Pier Luigi",
    "Victories": 1,
    "2nd places": 1,
    "3rd places": 2,
    "Pole positions from '74 to 2022": "",
    "Race fastest lap to 2022": "",
    "World Championships": ""
  },
  {
    "Riders All Time in All Classes": "GUILLEUX Herve",
    "Victories": 1,
    "2nd places": 1,
    "3rd places": 2,
    "Pole positions from '74 to 2022": "",
    "Race fastest lap to 2022": "",
    "World Championships": ""
  },
  {
    "Riders All Time in All Classes": "OETTL Philipp",
    "Victories": 1,
    "2nd places": 1,
    "3rd places": 1,
    "Pole positions from '74 to 2022": 1,
    "Race fastest lap to 2022": 2,
    "World Championships": ""
  },
  {
    "Riders All Time in All Classes": "CRAFAR Simon",
    "Victories": 1,
    "2nd places": 1,
    "3rd places": 1,
    "Pole positions from '74 to 2022": 1,
    "Race fastest lap to 2022": 2,
    "World Championships": ""
  },
  {
    "Riders All Time in All Classes": "AGOSTINI Duilio",
    "Victories": 1,
    "2nd places": 1,
    "3rd places": 1,
    "Pole positions from '74 to 2022": "",
    "Race fastest lap to 2022": 2,
    "World Championships": ""
  },
  {
    "Riders All Time in All Classes": "CLUZEL Jules",
    "Victories": 1,
    "2nd places": 1,
    "3rd places": 1,
    "Pole positions from '74 to 2022": "",
    "Race fastest lap to 2022": 1,
    "World Championships": ""
  },
  {
    "Riders All Time in All Classes": "TORRES Jordi",
    "Victories": 1,
    "2nd places": 1,
    "3rd places": 1,
    "Pole positions from '74 to 2022": "",
    "Race fastest lap to 2022": 1,
    "World Championships": ""
  },
  {
    "Riders All Time in All Classes": "BRUINS Jan",
    "Victories": 1,
    "2nd places": 1,
    "3rd places": 1,
    "Pole positions from '74 to 2022": "",
    "Race fastest lap to 2022": "",
    "World Championships": ""
  },
  {
    "Riders All Time in All Classes": "FÜGNER Horst",
    "Victories": 1,
    "2nd places": 1,
    "3rd places": 1,
    "Pole positions from '74 to 2022": "",
    "Race fastest lap to 2022": "",
    "World Championships": ""
  },
  {
    "Riders All Time in All Classes": "TOMIZAWA Shoya",
    "Victories": 1,
    "2nd places": 1,
    "3rd places": "",
    "Pole positions from '74 to 2022": 2,
    "Race fastest lap to 2022": "",
    "World Championships": ""
  },
  {
    "Riders All Time in All Classes": "GUEVARA Izan",
    "Victories": 1,
    "2nd places": 1,
    "3rd places": "",
    "Pole positions from '74 to 2022": 1,
    "Race fastest lap to 2022": 4,
    "World Championships": ""
  },
  {
    "Riders All Time in All Classes": "NAGASHIMA Tetsuta",
    "Victories": 1,
    "2nd places": 1,
    "3rd places": "",
    "Pole positions from '74 to 2022": 1,
    "Race fastest lap to 2022": 2,
    "World Championships": ""
  },
  {
    "Riders All Time in All Classes": "CHANTRA Somkiat",
    "Victories": 1,
    "2nd places": 1,
    "3rd places": "",
    "Pole positions from '74 to 2022": "",
    "Race fastest lap to 2022": 2,
    "World Championships": ""
  },
  {
    "Riders All Time in All Classes": "LOI Livio",
    "Victories": 1,
    "2nd places": 1,
    "3rd places": "",
    "Pole positions from '74 to 2022": "",
    "Race fastest lap to 2022": 1,
    "World Championships": ""
  },
  {
    "Riders All Time in All Classes": "NEWBOLD John",
    "Victories": 1,
    "2nd places": 1,
    "3rd places": "",
    "Pole positions from '74 to 2022": "",
    "Race fastest lap to 2022": 1,
    "World Championships": ""
  },
  {
    "Riders All Time in All Classes": "CREITH R.",
    "Victories": 1,
    "2nd places": 1,
    "3rd places": "",
    "Pole positions from '74 to 2022": "",
    "Race fastest lap to 2022": "",
    "World Championships": ""
  },
  {
    "Riders All Time in All Classes": "GOI Ivan",
    "Victories": 1,
    "2nd places": 1,
    "3rd places": "",
    "Pole positions from '74 to 2022": "",
    "Race fastest lap to 2022": "",
    "World Championships": ""
  },
  {
    "Riders All Time in All Classes": "FILICE Jim",
    "Victories": 1,
    "2nd places": 1,
    "3rd places": "",
    "Pole positions from '74 to 2022": "",
    "Race fastest lap to 2022": "",
    "World Championships": ""
  },
  {
    "Riders All Time in All Classes": "GUSTAFSSON Leif",
    "Victories": 1,
    "2nd places": 1,
    "3rd places": "",
    "Pole positions from '74 to 2022": "",
    "Race fastest lap to 2022": "",
    "World Championships": ""
  },
  {
    "Riders All Time in All Classes": "COLNAGO Giuseppe",
    "Victories": 1,
    "2nd places": 1,
    "3rd places": "",
    "Pole positions from '74 to 2022": "",
    "Race fastest lap to 2022": "",
    "World Championships": ""
  },
  {
    "Riders All Time in All Classes": "CASOLI Paolo",
    "Victories": 1,
    "2nd places": "",
    "3rd places": 4,
    "Pole positions from '74 to 2022": 1,
    "Race fastest lap to 2022": "",
    "World Championships": ""
  },
  {
    "Riders All Time in All Classes": "BAYLISS Troy",
    "Victories": 1,
    "2nd places": "",
    "3rd places": 4,
    "Pole positions from '74 to 2022": "",
    "Race fastest lap to 2022": "",
    "World Championships": ""
  },
  {
    "Riders All Time in All Classes": "RICCI Fausto",
    "Victories": 1,
    "2nd places": "",
    "3rd places": 4,
    "Pole positions from '74 to 2022": "",
    "Race fastest lap to 2022": "",
    "World Championships": ""
  },
  {
    "Riders All Time in All Classes": "VAN DONGEN Cees",
    "Victories": 1,
    "2nd places": "",
    "3rd places": 4,
    "Pole positions from '74 to 2022": "",
    "Race fastest lap to 2022": "",
    "World Championships": ""
  },
  {
    "Riders All Time in All Classes": "CELSO-SANTOS Adu",
    "Victories": 1,
    "2nd places": "",
    "3rd places": 2,
    "Pole positions from '74 to 2022": "",
    "Race fastest lap to 2022": "",
    "World Championships": ""
  },
  {
    "Riders All Time in All Classes": "DANIELL Harold",
    "Victories": 1,
    "2nd places": 2,
    "3rd places": "",
    "Pole positions from '74 to 2022": "",
    "Race fastest lap to 2022": "",
    "World Championships": ""
  },
  {
    "Riders All Time in All Classes": "ROBERTS Joe",
    "Victories": 1,
    "2nd places": 1,
    "3rd places": 3,
    "Pole positions from '74 to 2022": 1,
    "Race fastest lap to 2022": "",
    "World Championships": ""
  },
  {
    "Riders All Time in All Classes": "TAIRA Tadahiko",
    "Victories": 1,
    "2nd places": 1,
    "3rd places": 2,
    "Pole positions from '74 to 2022": 1,
    "Race fastest lap to 2022": "",
    "World Championships": ""
  },
  {
    "Riders All Time in All Classes": "LACONI Regis",
    "Victories": 1,
    "2nd places": 1,
    "3rd places": 1,
    "Pole positions from '74 to 2022": "",
    "Race fastest lap to 2022": "",
    "World Championships": ""
  },
  {
    "Riders All Time in All Classes": "PIRRO Michele",
    "Victories": 1,
    "2nd places": 1,
    "3rd places": 1,
    "Pole positions from '74 to 2022": "",
    "Race fastest lap to 2022": "",
    "World Championships": ""
  },
  {
    "Riders All Time in All Classes": "ARTIGAS Xavier",
    "Victories": 1,
    "2nd places": 1,
    "3rd places": "",
    "Pole positions from '74 to 2022": 2,
    "Race fastest lap to 2022": "",
    "World Championships": ""
  },
  {
    "Riders All Time in All Classes": "KOBAYASHI Masaru",
    "Victories": 1,
    "2nd places": 1,
    "3rd places": "",
    "Pole positions from '74 to 2022": 1,
    "Race fastest lap to 2022": "",
    "World Championships": ""
  },
  {
    "Riders All Time in All Classes": "MCCULLOUGH Ray",
    "Victories": 1,
    "2nd places": 1,
    "3rd places": "",
    "Pole positions from '74 to 2022": 1,
    "Race fastest lap to 2022": "",
    "World Championships": ""
  },
  {
    "Riders All Time in All Classes": "ABRAHAM Karel",
    "Victories": 1,
    "2nd places": 1,
    "3rd places": "",
    "Pole positions from '74 to 2022": 1,
    "Race fastest lap to 2022": "",
    "World Championships": ""
  },
  {
    "Riders All Time in All Classes": "NASH Godfrey",
    "Victories": 1,
    "2nd places": 1,
    "3rd places": "",
    "Pole positions from '74 to 2022": 1,
    "Race fastest lap to 2022": "",
    "World Championships": ""
  },
  {
    "Riders All Time in All Classes": "HASEGAWA Horoshi",
    "Victories": 1,
    "2nd places": 1,
    "3rd places": "",
    "Pole positions from '74 to 2022": 1,
    "Race fastest lap to 2022": "",
    "World Championships": ""
  },
  {
    "Riders All Time in All Classes": "EMMERICH Ingo",
    "Victories": 1,
    "2nd places": 1,
    "3rd places": "",
    "Pole positions from '74 to 2022": "",
    "Race fastest lap to 2022": "",
    "World Championships": ""
  },
  {
    "Riders All Time in All Classes": "KAFKA Gerd",
    "Victories": 1,
    "2nd places": 1,
    "3rd places": "",
    "Pole positions from '74 to 2022": "",
    "Race fastest lap to 2022": "",
    "World Championships": ""
  },
  {
    "Riders All Time in All Classes": "COPETA Angelo",
    "Victories": 1,
    "2nd places": 1,
    "3rd places": "",
    "Pole positions from '74 to 2022": "",
    "Race fastest lap to 2022": "",
    "World Championships": ""
  },
  {
    "Riders All Time in All Classes": "JEFFERIES Tony",
    "Victories": 1,
    "2nd places": 1,
    "3rd places": "",
    "Pole positions from '74 to 2022": "",
    "Race fastest lap to 2022": "",
    "World Championships": ""
  },
  {
    "Riders All Time in All Classes": "CARTER Alan",
    "Victories": 1,
    "2nd places": "",
    "3rd places": "",
    "Pole positions from '74 to 2022": 2,
    "Race fastest lap to 2022": "",
    "World Championships": ""
  },
  {
    "Riders All Time in All Classes": "BALLERINI Andrea",
    "Victories": 1,
    "2nd places": "",
    "3rd places": "",
    "Pole positions from '74 to 2022": 1,
    "Race fastest lap to 2022": "",
    "World Championships": ""
  },
  {
    "Riders All Time in All Classes": "STOELLINGER Edi",
    "Victories": 1,
    "2nd places": "",
    "3rd places": "",
    "Pole positions from '74 to 2022": 1,
    "Race fastest lap to 2022": "",
    "World Championships": ""
  },
  {
    "Riders All Time in All Classes": "SALA Guido",
    "Victories": 1,
    "2nd places": "",
    "3rd places": "",
    "Pole positions from '74 to 2022": 1,
    "Race fastest lap to 2022": "",
    "World Championships": ""
  },
  {
    "Riders All Time in All Classes": "MIYAZAKI Osamu",
    "Victories": 1,
    "2nd places": "",
    "3rd places": "",
    "Pole positions from '74 to 2022": 1,
    "Race fastest lap to 2022": "",
    "World Championships": ""
  },
  {
    "Riders All Time in All Classes": "REITMAIER Fritz",
    "Victories": 1,
    "2nd places": "",
    "3rd places": "",
    "Pole positions from '74 to 2022": 1,
    "Race fastest lap to 2022": "",
    "World Championships": ""
  },
  {
    "Riders All Time in All Classes": "ÖNCÜ Can",
    "Victories": 1,
    "2nd places": "",
    "3rd places": "",
    "Pole positions from '74 to 2022": 1,
    "Race fastest lap to 2022": "",
    "World Championships": ""
  },
  {
    "Riders All Time in All Classes": "MUDFORD Ken",
    "Victories": 1,
    "2nd places": "",
    "3rd places": "",
    "Pole positions from '74 to 2022": 1,
    "Race fastest lap to 2022": "",
    "World Championships": ""
  },
  {
    "Riders All Time in All Classes": "CZIHAK Edmund",
    "Victories": 1,
    "2nd places": "",
    "3rd places": "",
    "Pole positions from '74 to 2022": 1,
    "Race fastest lap to 2022": "",
    "World Championships": ""
  },
  {
    "Riders All Time in All Classes": "BARRINGTON Manliefe",
    "Victories": 1,
    "2nd places": "",
    "3rd places": "",
    "Pole positions from '74 to 2022": "",
    "Race fastest lap to 2022": "",
    "World Championships": ""
  },
  {
    "Riders All Time in All Classes": "IRELAND Dennis",
    "Victories": 1,
    "2nd places": "",
    "3rd places": "",
    "Pole positions from '74 to 2022": "",
    "Race fastest lap to 2022": "",
    "World Championships": ""
  },
  {
    "Riders All Time in All Classes": "ROSSI Louis",
    "Victories": 1,
    "2nd places": "",
    "3rd places": "",
    "Pole positions from '74 to 2022": "",
    "Race fastest lap to 2022": "",
    "World Championships": ""
  },
  {
    "Riders All Time in All Classes": "LEONI Guido",
    "Victories": 1,
    "2nd places": "",
    "3rd places": "",
    "Pole positions from '74 to 2022": "",
    "Race fastest lap to 2022": "",
    "World Championships": ""
  },
  {
    "Riders All Time in All Classes": "FELGENHEIER Roland",
    "Victories": 1,
    "2nd places": "",
    "3rd places": "",
    "Pole positions from '74 to 2022": "",
    "Race fastest lap to 2022": "",
    "World Championships": ""
  },
  {
    "Riders All Time in All Classes": "AUREAL Jean",
    "Victories": 1,
    "2nd places": "",
    "3rd places": "",
    "Pole positions from '74 to 2022": "",
    "Race fastest lap to 2022": "",
    "World Championships": ""
  },
  {
    "Riders All Time in All Classes": "CARPENTER Phil",
    "Victories": 1,
    "2nd places": "",
    "3rd places": "",
    "Pole positions from '74 to 2022": "",
    "Race fastest lap to 2022": "",
    "World Championships": ""
  }
]